folkol/grab.py
folkol.grab-0.0.5.dist-info/LICENSE.txt
folkol.grab-0.0.5.dist-info/METADATA
folkol.grab-0.0.5.dist-info/WHEEL
folkol.grab-0.0.5.dist-info/entry_points.txt
folkol.grab-0.0.5.dist-info/top_level.txt
folkol.grab-0.0.5.dist-info/RECORD
