Metadata-Version: 2.1
Name: folkol.grab
Version: 0.0.5
Summary: a unix filter for extracting tokens
Home-page: https://github.com/folkol/grab
Author: folkol
License: UNKNOWN
Project-URL: Bug Reports, https://github.com/folkol/grab/issues
Project-URL: Source, https://github.com/folkol/grab
Keywords: shell,unix filter
Platform: UNKNOWN
Classifier: Development Status :: 3 - Alpha
Classifier: Intended Audience :: Developers
Classifier: Topic :: Terminals
Classifier: Topic :: Text Processing :: Filters
Classifier: License :: OSI Approved :: MIT License
Requires-Python: >=3.6, <4
